AUTHORS.rst
CONTRIBUTING.rst
HISTORY.rst
koapy/__init__.py
koapy/backend/__init__.py
koapy/backend/daishin_cybos_plus/__init__.py
koapy/backend/daishin_cybos_plus/core/__init__.py
koapy/backend/daishin_cybos_plus/core/CybosPlusEntrypoint.py
koapy/backend/daishin_cybos_plus/core/CybosPlusEntrypointMixin.py
koapy/backend/daishin_cybos_plus/core/CybosPlusError.py
koapy/backend/daishin_cybos_plus/core/CybosPlusRateLimiter.py
koapy/backend/daishin_cybos_plus/proxy/__init__.py
koapy/backend/daishin_cybos_plus/proxy/CybosPlusEntrypointProxy.py
koapy/backend/daishin_cybos_plus/proxy/CybosPlusProxyService.proto
koapy/backend/daishin_cybos_plus/proxy/CybosPlusProxyService.py
koapy/backend/daishin_cybos_plus/proxy/CybosPlusProxyService_pb2.py
koapy/backend/daishin_cybos_plus/proxy/CybosPlusProxyService_pb2_grpc.py
koapy/backend/daishin_cybos_plus/proxy/CybosPlusProxyServiceMessageUtils.py
koapy/backend/daishin_cybos_plus/proxy/CybosPlusProxyServiceServicer.py
koapy/backend/kiwoom_open_api_plus/__init__.py
koapy/backend/kiwoom_open_api_plus/core/__init__.py
koapy/backend/kiwoom_open_api_plus/core/KiwoomOpenApiPlusCondition.py
koapy/backend/kiwoom_open_api_plus/core/KiwoomOpenApiPlusDispatchFunctions.py
koapy/backend/kiwoom_open_api_plus/core/KiwoomOpenApiPlusDispatchSignature.py
koapy/backend/kiwoom_open_api_plus/core/KiwoomOpenApiPlusDynamicCallable.py
koapy/backend/kiwoom_open_api_plus/core/KiwoomOpenApiPlusEntrypoint.py
koapy/backend/kiwoom_open_api_plus/core/KiwoomOpenApiPlusEntrypointMixin.py
koapy/backend/kiwoom_open_api_plus/core/KiwoomOpenApiPlusError.py
koapy/backend/kiwoom_open_api_plus/core/KiwoomOpenApiPlusEventFunctions.py
koapy/backend/kiwoom_open_api_plus/core/KiwoomOpenApiPlusEventHandler.py
koapy/backend/kiwoom_open_api_plus/core/KiwoomOpenApiPlusEventHandlerFunctions.py
koapy/backend/kiwoom_open_api_plus/core/KiwoomOpenApiPlusEventHandlerSignature.py
koapy/backend/kiwoom_open_api_plus/core/KiwoomOpenApiPlusLoggingEventHandler.py
koapy-0.9.0.dist-info/entry_points.txt
koapy-0.9.0.dist-info/LICENSE.MIT
koapy-0.9.0.dist-info/LICENSE.GPL-3.0-OR-LATER
koapy-0.9.0.dist-info/LICENSE
koapy-0.9.0.dist-info/LICENSE.APACHE-2.0
koapy-0.9.0.dist-info/WHEEL
koapy-0.9.0.dist-info/METADATA
koapy-0.9.0.dist-info/RECORD
