Metadata-Version: 2.1
Name: koapy
Version: 0.9.0
Summary: Kiwoom Open Api Plus Python
Home-page: https://github.com/elbakramer/koapy
License: MIT OR Apache-2.0 OR GPL-3.0-or-later
Keywords: kiwoom,kiwoom-open-api
Author: Yunseong Hwang
Author-email: kika1492@gmail.com
Maintainer: Yunseong Hwang
Maintainer-email: kika1492@gmail.com
Requires-Python: >=3.8.1,<3.11
Classifier: Development Status :: 2 - Pre-Alpha
Classifier: Environment :: Console
Classifier: Environment :: X11 Applications :: Qt
Classifier: Intended Audience :: Developers
Classifier: License :: OSI Approved :: Apache Software License
Classifier: License :: OSI Approved :: GNU General Public License v3 or later (GPLv3+)
Classifier: License :: OSI Approved :: MIT License
Classifier: License :: Other/Proprietary License
Classifier: Natural Language :: English
Classifier: Natural Language :: Korean
Classifier: Operating System :: Microsoft :: Windows :: Windows 10
Classifier: Programming Language :: Python :: 3
Classifier: Programming Language :: Python :: 3.10
Classifier: Programming Language :: Python :: 3.8
Classifier: Programming Language :: Python :: 3.9
Classifier: Topic :: Office/Business :: Financial
Requires-Dist: PySide2 (>=5.15.2.1,<6.0.0.0)
Requires-Dist: QtPy (>=2.2.0,<3.0.0)
Requires-Dist: Rx (>=3.2.0,<4.0.0)
Requires-Dist: SQLAlchemy (>=1.4.41,<2.0.0)
Requires-Dist: Send2Trash (>=1.8.0,<2.0.0)
Requires-Dist: click (>=8.1.3,<9.0.0)
Requires-Dist: cryptography (>=38.0.1,<39.0.0)
Requires-Dist: deprecated (>=1.2.13,<2.0.0)
Requires-Dist: discord.py (>=2.0.1,<3.0.0)
Requires-Dist: exchange-calendars (>=4.2,<5.0)
Requires-Dist: grpcio (>=1.48.1,<2.0.0)
Requires-Dist: grpcio-tools (>=1.48.1,<2.0.0)
Requires-Dist: lxml (>=4.9.1,<5.0.0)
Requires-Dist: numpy (>=1.23.3,<2.0.0)
Requires-Dist: openpyxl (>=3.0.10,<4.0.0)
Requires-Dist: pandas (>=1.4.4,<2.0.0)
Requires-Dist: psutil (>=5.9.0,<6.0.0)
Requires-Dist: pygtrie (>=2.5.0,<3.0.0)
Requires-Dist: pyhocon (>=0.3.59,<0.4.0)
Requires-Dist: pytz (>=2022.2.1,<2023.0.0)
Requires-Dist: pywin32 (>=304,<305); sys_platform == "win32"
Requires-Dist: pywinauto (>=0.6.8,<0.7.0); sys_platform == "win32"
Requires-Dist: requests (>=2.28.1,<3.0.0)
Requires-Dist: schedule (>=1.1.0,<2.0.0)
Requires-Dist: tabulate (>=0.8.10,<0.9.0)
Requires-Dist: tqdm (>=4.64.1,<5.0.0)
Requires-Dist: typing-extensions (>=4.3.0,<5.0.0); python_version < "3.10"
Requires-Dist: tzlocal (>=4.2,<5.0)
Requires-Dist: windows-curses (>=2.3.0,<3.0.0); sys_platform == "win32"
Requires-Dist: wrapt (>=1.14.1,<2.0.0)
Project-URL: Bug Tracker, https://github.com/elbakramer/koapy/issues
Project-URL: Documentation, https://koapy.readthedocs.io/en/latest/
Project-URL: Repository, https://github.com/elbakramer/koapy
